jwe_crypto/__init__.py
kms_crypto/__init__.py
jwe_encryptify-0.0.3.dist-info/METADATA
jwe_encryptify-0.0.3.dist-info/WHEEL
jwe_encryptify-0.0.3.dist-info/top_level.txt
jwe_encryptify-0.0.3.dist-info/RECORD
