Metadata-Version: 2.1
Name: jwe-encryptify
Version: 0.0.3
Summary: A Python package to facilitate JSON Web Encryption (JWE) with enhanced security, leveraging AWS Key Management Service (KMS) and Secrets Manager for secure input and output handling.
Author: M Santhosh Kumar
Author-email: santhoshse7en@gmail.com
Project-URL: Documentation, https://github.com/santhoshse7en/jwe-encryptify#readme
Project-URL: Source, https://github.com/santhoshse7en/jwe-encryptify
Project-URL: Tracker, https://github.com/santhoshse7en/jwe-encryptify/issues
Keywords: JWE,KMS,Secret Manager,Encryption,AWS,Cryptography
Classifier: Development Status :: 4 - Beta
Classifier: Intended Audience :: Developers
Classifier: Intended Audience :: System Administrators
Classifier: License :: OSI Approved :: MIT License
Classifier: Operating System :: OS Independent
Classifier: Programming Language :: Python :: 3
Classifier: Topic :: Security :: Cryptography
Classifier: Topic :: Software Development :: Libraries :: Python Modules
Requires-Python: >=3.9
Requires-Dist: jwcrypto
Requires-Dist: boto3
Requires-Dist: botocore
